my_pypi/__init__.py
my_pypi/module1.py
my_pypi/module2.py
Packist-0.1.1.dist-info/METADATA
Packist-0.1.1.dist-info/WHEEL
Packist-0.1.1.dist-info/top_level.txt
Packist-0.1.1.dist-info/RECORD
